{
  "name": "John Doe",
  "image": "",
  "birthdate": "1990-01-01",
  "address": "1234 Main St, New York, NY 10001",
  "phone": "123-456-7890",
  "email": "john@doe.com",
  "nation": "Norway",
  "height": 180,
  "weight": 75,
  "dominantFoot": "Right",
  "team": "Manchester United",
  "league": "Premier League",
  "position": "Midfielder",
  "seasons": [
    {
      "title": "2025",
      "matches": [
        {
          "home": "Manchester United",
          "away": "Liverpool",
          "homeScore": 2,
          "awayScore": 1,
          "date": "2025-01-01",
          "playTime": 83,
          "position": "Midfielder",
          "events": [
            {
              "event": "Goal",
              "time": "12:05",
              "notes": "Header"
            },
            {
              "event": "Yellow Card",
              "time": "44:12",
              "notes": "Foul"
            },
            {
              "event": "Assist",
              "time": "56:32",
              "notes": ""
            },
            {
              "event": "Goal",
              "time": "78:23",
              "notes": "Penalty"
            }
          ],
          "tracking": [
            {
              "coordinations": {
                "x": 0,
                "y": 0,
                "z": 0
              },
              "timestamp": "13:29",
              "speed": 12
            },
            {
              "coordinations": {
                "x": 1,
                "y": 1,
                "z": 0
              },
              "timestamp": "13:30",
              "speed": 12
            },
            {
              "coordinations": {
                "x": 2,
                "y": 2,
                "z": 0
              },
              "timestamp": "13:31",
              "speed": 12
            },
            {
              "coordinations": {
                "x": 3,
                "y": 3,
                "z": 0
              },
              "timestamp": "13:32",
              "speed": 13
            },
            {
              "coordinations": {
                "x": 5,
                "y": 5,
                "z": 0
              },
              "timestamp": "13:33",
              "speed": 13
            },
            {
              "coordinations": {
                "x": 7,
                "y": 7,
                "z": 0
              },
              "timestamp": "13:34",
              "speed": 13
            },
            {
              "coordinations": {
                "x": 9,
                "y": 9,
                "z": 0
              },
              "timestamp": "13:35",
              "speed": 12
            },
            {
              "coordinations": {
                "x": 10,
                "y": 10,
                "z": 0
              },
              "timestamp": "13:36",
              "speed": 12
            }
          ],
          "biometric": [
            {
              "type": "Heart Rate",
              "value": 120,
              "timestamp": "29:00"
            },
            {
              "type": "Body Temperature",
              "value": 36.5,
              "timestamp": "29:00"
            },
            {
              "type": "Blood Pressure",
              "value": "120/80",
              "timestamp": "29:00"
            },
            {
              "type": "Heart Rate",
              "value": 130,
              "timestamp": "30:00"
            },
            {
              "type": "Body Temperature",
              "value": 36.6,
              "timestamp": "30:00"
            },
            {
              "type": "Blood Pressure",
              "value": "120/80",
              "timestamp": "30:00"
            }
          ]
        },
        {
          "home": "Manchester United",
          "away": "Chelsea",
          "homeScore": 1,
          "awayScore": 1,
          "date": "2025-01-05",
          "playTime": 95,
          "position": "Midfielder",
          "events": [
            {
              "event": "Free Kick",
              "time": "22:05",
              "notes": ""
            },
            {
              "event": "Goal",
              "time": "65:59",
              "notes": ""
            },
            {
              "event": "Free Kick",
              "time": "72:43",
              "notes": "Right pole and out"
            },
            {
              "event": "Assist",
              "time": "92:01",
              "notes": ""
            }
          ],
          "tracking": [
            {
              "coordinations": {
                "x": 0,
                "y": 0,
                "z": 0
              },
              "timestamp": "05:23",
              "speed": 12
            },
            {
              "coordinations": {
                "x": 1,
                "y": 1,
                "z": 0
              },
              "timestamp": "05:24",
              "speed": 12
            },
            {
              "coordinations": {
                "x": 2,
                "y": 2,
                "z": 0
              },
              "timestamp": "05:25",
              "speed": 12
            },
            {
              "coordinations": {
                "x": 3,
                "y": 3,
                "z": 0
              },
              "timestamp": "05:26",
              "speed": 13
            },
            {
              "coordinations": {
                "x": 5,
                "y": 5,
                "z": 0
              },
              "timestamp": "05:27",
              "speed": 13
            },
            {
              "coordinations": {
                "x": 7,
                "y": 7,
                "z": 0
              },
              "timestamp": "05:28",
              "speed": 13
            },
            {
              "coordinations": {
                "x": 9,
                "y": 9,
                "z": 0
              },
              "timestamp": "05:29",
              "speed": 12
            },
            {
              "coordinations": {
                "x": 10,
                "y": 10,
                "z": 0
              },
              "timestamp": "05:30",
              "speed": 12
            }
          ],
          "biometric": [
            {
              "type": "Heart Rate",
              "value": 120,
              "timestamp": "29:00"
            },
            {
              "type": "Body Temperature",
              "value": 36.5,
              "timestamp": "29:00"
            },
            {
              "type": "Blood Pressure",
              "value": "120/80",
              "timestamp": "29:00"
            },
            {
              "type": "Heart Rate",
              "value": 130,
              "timestamp": "30:00"
            },
            {
              "type": "Body Temperature",
              "value": 36.6,
              "timestamp": "30:00"
            },
            {
              "type": "Blood Pressure",
              "value": "120/80",
              "timestamp": "30:00"
            }
          ]
        }
      ],
      "training": [
        {
          "tracking": [
            {
              "coordinations": {
                "x": 0,
                "y": 0,
                "z": 0
              },
              "timestamp": "13:29",
              "speed": 12
            },
            {
              "coordinations": {
                "x": 1,
                "y": 1,
                "z": 0
              },
              "timestamp": "13:30",
              "speed": 12
            },
            {
              "coordinations": {
                "x": 2,
                "y": 2,
                "z": 0
              },
              "timestamp": "13:31",
              "speed": 12
            },
            {
              "coordinations": {
                "x": 3,
                "y": 3,
                "z": 0
              },
              "timestamp": "13:32",
              "speed": 13
            },
            {
              "coordinations": {
                "x": 5,
                "y": 5,
                "z": 0
              },
              "timestamp": "13:33",
              "speed": 13
            },
            {
              "coordinations": {
                "x": 7,
                "y": 7,
                "z": 0
              },
              "timestamp": "13:34",
              "speed": 13
            },
            {
              "coordinations": {
                "x": 9,
                "y": 9,
                "z": 0
              },
              "timestamp": "13:35",
              "speed": 12
            },
            {
              "coordinations": {
                "x": 10,
                "y": 10,
                "z": 0
              },
              "timestamp": "13:36",
              "speed": 12
            }
          ],
          "biometric": [
            {
              "type": "Heart Rate",
              "value": 120,
              "timestamp": "29:00"
            },
            {
              "type": "Body Temperature",
              "value": 36.5,
              "timestamp": "29:00"
            },
            {
              "type": "Blood Pressure",
              "value": "120/80",
              "timestamp": "29:00"
            },
            {
              "type": "Heart Rate",
              "value": 130,
              "timestamp": "30:00"
            },
            {
              "type": "Body Temperature",
              "value": 36.6,
              "timestamp": "30:00"
            },
            {
              "type": "Blood Pressure",
              "value": "120/80",
              "timestamp": "30:00"
            }
          ]
        }
      ]
    }
  ]
}
